{
  "exportedAt": "2026-05-08 18:53:02",
  "series": {
    "desktop": {
      "count": 500,
      "totalViews": 14684,
      "totalDownloads": 5042
    },
    "mobile": {
      "count": 500,
      "totalViews": 9330,
      "totalDownloads": 2796
    },
    "avatar": {
      "count": 393,
      "totalViews": 1247,
      "totalDownloads": 552
    },
    "video": {
      "count": 16,
      "totalViews": 293,
      "totalDownloads": 12
    },
    "bing": {
      "count": 497,
      "totalViews": 1411,
      "totalDownloads": 758
    }
  }
}